Metadata-Version: 2.1
Name: araby-ai
Version: 0.0.4
Summary: With this library, You can use all the services of the Araby-ai site in Python with ease
Author: VIRUS
Classifier: Programming Language :: Python :: 3
Classifier: Operating System :: OS Independent
Classifier: License :: OSI Approved :: MIT License
License-File: LICENSE.txt
